labs/lab3/fpga/sim/cols_sync.sv
// -------------------------------------------------------------
// cols_sync.sv  
// Author: Haspard Murphy <hmurphy@g.hmc.edu>
// Date:   2026-09-21
// Course: HMC E155, Lab 3
// Purpose: Syncronizer module for asyncnronous column input (key presses)
// 2 staged D-Flip Flops
// -------------------------------------------------------------
module cols_sync(input logic clk,
                input logic reset,
                input logic [3:0] cols_in, // async input column signlas from toggled keys
                output logic [3:0] cols_synced); //syncronized ouput column signals

                logic [3:0] cols_inter; //intermediary signals between FF's

        always_ff @(posedge clk) begin
             if (reset) begin
                cols_synced <= 4'b0000;
                cols_inter <= 4'b0000;
            end
            else begin
                cols_inter <= cols_in;
                cols_synced <= cols_inter;
            end
        end

endmodule

labs/lab3/fpga/radiant/testbenches/cols_tb.sv
// -------------------------------------------------------------
// cols_tb.sv  
// Author: Haspard Murphy <hmurphy@g.hmc.edu>
// Date:   2026-09-22
// Course: HMC E155, Lab 3
// Purpose: Testbench for column input synchronizer
// -------------------------------------------------------------
`timescale 1ns/1ns
`default_nettype none

module cols_tb;
        logic clk;
        logic reset;
        logic [3:0] cols_in;
        logic [3:0] cols_synced;

        int errors = 0;

        cols_sync dut (.clk(clk), .reset(reset), .cols_in(cols_in), 
        .cols_synced(cols_synced));

        always #5 clk = ~clk;

        initial begin
            clk = 0;
            reset = 0;
            cols_in = 0;
            
            #20;
            reset = 1;
            #15;
            
            // One key pressed
            reset = 0;
            @(posedge clk);
            cols_in = 4'b1110;
            @(posedge clk); @(posedge clk); 
            #1;
            assert (cols_synced == 4'b1110)
                $display("PASSED! At time: %0t.", $time);
            else begin
                $error("FAILED! At time: %0t.", $time); 
                errors++;
            end

            #20;

            // No key pressed
            @(posedge clk);
            cols_in = 4'b1111;
            @(posedge clk); @(posedge clk); 
            #1;
            assert (cols_synced == 4'b1111)
                $display("PASSED! At time: %0t.", $time);
            else begin
                $error("FAILED! At time: %0t.", $time); 
                errors++;
            end

            if (errors == 0) $display("cols_tb PASSED");
            else             $display("cols_tb FAILED: %0d errors", errors);
            $finish;
        end
        initial begin
            $dumpfile("cols_tb.vcd");
            $dumpvars(0, cols_tb);
        end
endmodule

labs/lab3/fpga/sim/lab3_sim_cols/cols_tb.vcd
$date
	Tue Sep 22 23:35:42 2026
$end
$version
	Questa Lattice OEM Edition 2025.2
$end
$timescale
	1ns
$end

$scope module cols_tb $end
$var reg 1 ! clk $end
$var reg 1 " reset $end
$var reg 4 # cols_in [3:0] $end
$var reg 4 $ cols_synced [3:0] $end
$var integer 32 % errors $end

$scope module dut $end
$var wire 1 & clk $end
$var wire 1 ' reset $end
$var wire 1 ( cols_in [3] $end
$var wire 1 ) cols_in [2] $end
$var wire 1 * cols_in [1] $end
$var wire 1 + cols_in [0] $end
$var reg 4 , cols_synced [3:0] $end
$var reg 4 - cols_inter [3:0] $end
$upscope $end
$upscope $end
$enddefinitions $end
#0
$dumpvars
0!
0"
b0 #
bx $
bx ,
bx -
b0 %
0+
0*
0)
0(
0'
0&
$end
#5
1!
1&
b0 -
#10
0!
0&
#15
1!
1&
b0 ,
b0 $
#20
1"
0!
1'
0&
#25
1!
1&
#30
0!
0&
#35
0"
1!
0'
1&
b1110 #
1*
1)
1(
#40
0!
0&
#45
1!
1&
b1110 -
#50
0!
0&
#55
1!
1&
b1110 ,
b1110 $
#60
0!
0&
#65
1!
1&
#70
0!
0&
#75
1!
1&
#80
0!
0&
#85
1!
1&
b1111 #
1+
#90
0!
0&
#95
1!
1&
b1111 -
#100
0!
0&
#105
1!
1&
b1111 ,
b1111 $
