labs/lab3/fpga/sim/reset_sync.sv
// -------------------------------------------------------------
// reset_sync.sv  
// Author: Haspard Murphy <hmurphy@g.hmc.edu>
// Date:   2026-09-21
// Course: HMC E155, Lab 3
// Purpose: 2-FF Syncronizer module for asyncnronous reset input
// -------------------------------------------------------------
module reset_sync(input logic clk,
                input logic reset,
                output logic reset_synced); //syncronized ouput reset signal

                logic reset_inter; //intermediary signals between FF's

        always_ff @(posedge clk) begin
                reset_inter <= reset;
                reset_synced <= reset_inter;
        end

endmodule

labs/lab3/fpga/radiant/testbenches/rst_tb.sv
// -------------------------------------------------------------
// rst_tb.sv  
// Author: Haspard Murphy <hmurphy@g.hmc.edu>
// Date:   2026-09-22
// Course: HMC E155, Lab 3
// Purpose: Testbench for reset synchronizer
// -------------------------------------------------------------
`timescale 1ns/1ns
`default_nettype none

module rst_tb;
        logic clk;
        logic reset;
        logic reset_synced;

        int errors = 0;

        reset_sync dut (.clk(clk), .reset(reset), .reset_synced(reset_synced));

        always #5 clk = ~clk;

        initial begin
            clk = 0;
            reset = 0;
            
            #20;
            
            // Reset button pressed
            @(posedge clk);
            reset = 1;
            @(posedge clk); @(posedge clk); 
            #1;
            assert (reset_synced == 1'b1)
                $display("PASSED! At time: %0t.", $time);
            else begin
                $error("FAILED! At time: %0t.", $time); 
                errors++;
            end

            #20;
            
            // Reset button released
            @(posedge clk);
            reset = 0;
            @(posedge clk); @(posedge clk); 
            #1;
            assert (reset_synced == 1'b0)
                $display("PASSED! At time: %0t.", $time);
            else begin
                $error("FAILED! At time: %0t.", $time); 
                errors++;
            end

            if (errors == 0) $display("rst_tb PASSED");
            else             $display("rst_tb FAILED: %0d errors", errors);
            $finish;
        end
        initial begin
            $dumpfile("rst_tb.vcd");
            $dumpvars(0, rst_tb);
        end
endmodule

labs/lab3/fpga/sim/lab3_sim_reset/rst_tb.vcd
$date
	Tue Sep 22 23:38:12 2026
$end
$version
	Questa Lattice OEM Edition 2025.2
$end
$timescale
	1ns
$end

$scope module rst_tb $end
$var reg 1 ! clk $end
$var reg 1 " reset $end
$var reg 1 # reset_synced $end
$var integer 32 $ errors $end

$scope module dut $end
$var wire 1 % clk $end
$var wire 1 & reset $end
$var reg 1 ' reset_synced $end
$var reg 1 ( reset_inter $end
$upscope $end
$upscope $end
$enddefinitions $end
#0
$dumpvars
0!
0"
x#
x'
x(
b0 $
0&
0%
$end
#5
1!
1%
0(
#10
0!
0%
#15
1!
1%
0'
0#
#20
0!
0%
#25
1!
1%
1"
1&
#30
0!
0%
#35
1!
1%
1(
#40
0!
0%
#45
1!
1%
1'
1#
#50
0!
0%
#55
1!
1%
#60
0!
0%
#65
1!
1%
#70
0!
0%
#75
1!
1%
0"
0&
#80
0!
0%
#85
1!
1%
0(
#90
0!
0%
#95
1!
1%
0'
0#
